MANIFEST.in
README.rst
requirements.txt
setup.py
dbaas_nfsaas/__init__.py
dbaas_nfsaas/dbaas_api.py
dbaas_nfsaas/errors.py
dbaas_nfsaas/faas_provider.py
dbaas_nfsaas/models.py
dbaas_nfsaas.egg-info/PKG-INFO
dbaas_nfsaas.egg-info/SOURCES.txt
dbaas_nfsaas.egg-info/dependency_links.txt
dbaas_nfsaas.egg-info/not-zip-safe
dbaas_nfsaas.egg-info/requires.txt
dbaas_nfsaas.egg-info/top_level.txt
dbaas_nfsaas/migrations/0001_initial.py
dbaas_nfsaas/migrations/0002_auto__del_unique_hostattr_host.py
dbaas_nfsaas/migrations/0003_auto__add_field_hostattr_is_active.py
dbaas_nfsaas/migrations/0004_auto__add_field_hostattr_nfsaas_team_id__add_field_hostattr_nfsaas_pro.py
dbaas_nfsaas/migrations/0005_auto__add_field_hostattr_nfsaas_size_kb__chg_field_hostattr_nfsaas_siz.py
dbaas_nfsaas/migrations/0006_auto__add_field_hostattr_nfsaas_path_host.py
dbaas_nfsaas/migrations/0007_auto__add_field_hostattr_nfsaas_used_size_kb.py
dbaas_nfsaas/migrations/0008_auto__del_field_hostattr_nfsaas_team_id__del_field_hostattr_nfsaas_env.py
dbaas_nfsaas/migrations/0009_auto__del_planattr.py
dbaas_nfsaas/migrations/0010_auto__del_environmentattr.py
dbaas_nfsaas/migrations/0011_auto__add_group__add_field_hostattr_group.py
dbaas_nfsaas/migrations/__init__.py
dbaas_nfsaas/migrations/migration_0004_up.sql
dbaas_nfsaas/util/__init__.py
dbaas_nfsaas/util/models.py