Metadata-Version: 1.1
Name: dbaas-nfsaas
Version: 0.7.10
Summary: NFSaaS integration for DBaaS
Home-page: https://github.com/globocom/dbaas-nfsaas
Author: Mauro Andre Murari
Author-email: mauro_murari@hotmail.com
License: BSD
Keywords: dbaas_nfsaas
Platform: UNKNOWN
Classifier: Development Status :: 2 - Pre-Alpha
Classifier: Intended Audience :: Developers
Classifier: License :: OSI Approved :: BSD License
Classifier: Natural Language :: English
Classifier: Programming Language :: Python :: 2
Classifier: Programming Language :: Python :: 2.6
Classifier: Programming Language :: Python :: 2.7
Classifier: Programming Language :: Python :: 3
Classifier: Programming Language :: Python :: 3.3
